django_easy_jsonfield-0.0.2.dist-info/DESCRIPTION.rst
django_easy_jsonfield-0.0.2.dist-info/METADATA
django_easy_jsonfield-0.0.2.dist-info/RECORD
django_easy_jsonfield-0.0.2.dist-info/WHEEL
django_easy_jsonfield-0.0.2.dist-info/metadata.json
django_easy_jsonfield-0.0.2.dist-info/top_level.txt
easy_jsonfield/__init__.py
easy_jsonfield/encoder.py
easy_jsonfield/fields.py
easy_jsonfield/forms.py
tests/__init__.py
tests/models.py
tests/settings.py
tests/test_jsonfield.py
