Metadata-Version: 1.1
Name: django-easy-jsonfield
Version: 0.0.2
Summary: A fork of rpkilby's jsonfield2 (https://github.com/rpkilby/jsonfield2/), Aims to provide an easy django JSONField
Home-page: https://github.com/claydodo/easy_jsonfield
Author: claydodo and his little friends (xiao huo ban)
Author-email: claydodo@foxmail.com
License: UNKNOWN
Platform: UNKNOWN
Classifier: Programming Language :: Python :: 2.7 
Classifier: Programming Language :: Python :: 3 
Classifier: Operating System :: OS Independent
